bytedance_butterfly_dify_plugin/__init__.py
bytedance_butterfly_dify_plugin-0.0.1.dist-info/METADATA
bytedance_butterfly_dify_plugin-0.0.1.dist-info/WHEEL
bytedance_butterfly_dify_plugin-0.0.1.dist-info/top_level.txt
bytedance_butterfly_dify_plugin-0.0.1.dist-info/RECORD
