Metadata-Version: 2.1
Name: bytedance-butterfly-dify-plugin
Version: 0.0.1
Summary: A simple package named bytedance_butterfly_dify_plugin
Home-page: https://github.com/artifact/bytedance_butterfly_dify_plugin.git
Author: artifact
Author-email: artifact@example.com
License: UNKNOWN
Platform: UNKNOWN
Classifier: Programming Language :: Python :: 3
Classifier: License :: OSI Approved :: MIT License
Classifier: Operating System :: OS Independent
